Metadata-Version: 2.1
Name: olc
Version: 0.0.3
Summary: Basic Open Source License Collector
Home-page: https://github.com/rommelag/olc
Author: Rommelag iLabs
License: 0BSD
Platform: UNKNOWN
